odoo/addons/beesdoo_product_info_screen/README.rst
odoo/addons/beesdoo_product_info_screen/__init__.py
odoo/addons/beesdoo_product_info_screen/__manifest__.py
odoo/addons/beesdoo_product_info_screen/i18n/beesdoo_product_info_screen.pot
odoo/addons/beesdoo_product_info_screen/readme/CONTRIBUTORS.rst
odoo/addons/beesdoo_product_info_screen/readme/DESCRIPTION.rst
odoo/addons/beesdoo_product_info_screen/readme/USAGE.rst
odoo/addons/beesdoo_product_info_screen/security/groups.xml
odoo/addons/beesdoo_product_info_screen/security/ir.model.access.csv
odoo/addons/beesdoo_product_info_screen/security/ir_rules.xml
odoo/addons/beesdoo_product_info_screen/static/description/icon.png
odoo/addons/beesdoo_product_info_screen/static/description/index.html
odoo/addons/beesdoo_product_info_screen/views/menus.xml
odoo/addons/beesdoo_product_info_screen/views/product.xml
odoo12_addon_beesdoo_product_info_screen-12.0.0.0.1.99.dev11.dist-info/METADATA
odoo12_addon_beesdoo_product_info_screen-12.0.0.0.1.99.dev11.dist-info/WHEEL
odoo12_addon_beesdoo_product_info_screen-12.0.0.0.1.99.dev11.dist-info/top_level.txt
odoo12_addon_beesdoo_product_info_screen-12.0.0.0.1.99.dev11.dist-info/RECORD
